{
    "type": "cobblemon:cooking_pot_shapeless",
    "category": "misc",
    "ingredients": [
        {
            "item": "cobblemon:medicinal_brew"
        },
        {
            "item": "minecraft:sugar"
        },
        {
            "item": "minecraft:sugar"
        },
        {
            "item": "cobblemon:pomeg_berry"
        },
        {
            "item": "cobblemon:pomeg_berry"
        },
        {
            "item": "cobblemon:white_mint_leaf"
        }
    ],
    "result": {
        "id": "cobblemon:hp_up"
    },
    "seasoningProcessors": []
}